textcortex/__init__.py
textcortex/textcortex.py
textcortex-2.0.0.dist-info/LICENSE
textcortex-2.0.0.dist-info/METADATA
textcortex-2.0.0.dist-info/WHEEL
textcortex-2.0.0.dist-info/top_level.txt
textcortex-2.0.0.dist-info/RECORD
