Metadata-Version: 2.1
Name: textcortex
Version: 2.0.0
Summary: Generate product descriptions, blogs, emails, ads and more using GPT architecture with a single request to TextCortex API a.k.a Hemingwai
Home-page: https://github.com/textcortex/hemingwai
Author: TextCortex AI
Author-email: dev@textcortex.com
License: MIT
Keywords: TextCortex AI,gpt-2,gpt-3,gptNEO,generate text,natural language generation,NLP,hemingwai,transformer,generate copy text using AI
Platform: UNKNOWN
Classifier: Development Status :: 3 - Alpha
Classifier: Intended Audience :: Customer Service
Classifier: Intended Audience :: Information Technology
Classifier: Topic :: Scientific/Engineering :: Artificial Intelligence
Classifier: Natural Language :: English
Classifier: Programming Language :: Python :: 2
Classifier: Programming Language :: Python :: 3
Classifier: Operating System :: MacOS :: MacOS X
Classifier: Operating System :: Microsoft :: Windows
Classifier: Programming Language :: Python :: 3
License-File: LICENSE
Requires-Dist: requests
